{
 "_doc": "고전 문학 1주차 · 고대가요. 교재(0708판) 쪽 기준 재배치. title=작품명(출처), label=교재 문항번호, area=갈래.",
 "courseId": "hanti-dan-h1-gojeonmunhak",
 "week": 1,
 "weekMeta": {
  "id": "hanti-dan-h1-gojeonmunhak-w1",
  "label": "1주차 · 고대가요",
  "area": "고대가요",
  "date": "",
  "desc": "고전 문학 1주차 · 고대가요"
 },
 "scoring": {
  "passRate": 80
 },
 "sections": [
  {
   "key": "s1",
   "title": "정읍사 (2012년 고1 9월 학평)",
   "range": "2012년 고1 9월 학평",
   "questions": [
    {
     "no": 1,
     "id": "G1-1",
     "three": false,
     "wr": null,
     "area": "고대가요",
     "type": "",
     "source": "2012년 고1 9월 학평",
     "in_typebook": false,
     "coreElement": "",
     "weakness1": "고대가요 세트의 감상·분석 문항입니다. 틀렸다면 아래 해설로 작품 해석을 다시 확인하세요.",
     "weakness2": "",
     "remediation": "(가)·(나)·(다)는 모두 임이 곁에 없는 부재(不在)의 상황에 놓여 있고, 화자는 그 임과 다시 만나기를 간절히 소망한다. 따라서 ‘임의 부재 속에서 재회를 소망함’이 세 작품을 관통하는 공통점이다.",
     "parentNote": "",
     "note": "",
     "해설": "(가)·(나)·(다)는 모두 임이 곁에 없는 부재(不在)의 상황에 놓여 있고, 화자는 그 임과 다시 만나기를 간절히 소망한다. 따라서 ‘임의 부재 속에서 재회를 소망함’이 세 작품을 관통하는 공통점이다.",
     "answer": "",
     "label": "1번"
    },
    {
     "no": 2,
     "id": "G1-2",
     "three": false,
     "wr": null,
     "area": "고대가요",
     "type": "",
     "source": "2012년 고1 9월 학평",
     "in_typebook": false,
     "coreElement": "",
     "weakness1": "고대가요 세트의 감상·분석 문항입니다. 틀렸다면 아래 해설로 작품 해석을 다시 확인하세요.",
     "weakness2": "",
     "remediation": "(가)는 ‘나무리면~잊었노라’에서, (나)는 ‘이별이, 이별이’, ‘허이연 허이연’, ‘∼있어야 하네’에서 동일한 시구를 거듭 제시한다. 같은 구절을 반복하면 음악적 리듬, 곧 운율감이 형성되므로 두 작품의 공통된 표현상 특징은 ‘동일 시구의 반복을 통한 운율 형성’이다.",
     "parentNote": "",
     "note": "",
     "해설": "(가)는 ‘나무리면~잊었노라’에서, (나)는 ‘이별이, 이별이’, ‘허이연 허이연’, ‘∼있어야 하네’에서 동일한 시구를 거듭 제시한다. 같은 구절을 반복하면 음악적 리듬, 곧 운율감이 형성되므로 두 작품의 공통된 표현상 특징은 ‘동일 시구의 반복을 통한 운율 형성’이다.",
     "answer": "",
     "label": "2번"
    },
    {
     "no": 3,
     "id": "G1-3",
     "three": false,
     "wr": null,
     "area": "고대가요",
     "type": "",
     "source": "2012년 고1 9월 학평",
     "in_typebook": false,
     "coreElement": "",
     "weakness1": "고대가요 세트의 감상·분석 문항입니다. 틀렸다면 아래 해설로 작품 해석을 다시 확인하세요.",
     "weakness2": "",
     "remediation": "화자는 지금도 지속되는 이별을 인정하지 못하고 ‘먼 후일’이라는 미래를 설정한 뒤, 그때 가서 ‘잊었노라’ 말하겠다고 한다. 그러나 그 미래에도 결코 잊지 못할 임이기에 ‘잊었노라’는 반어적 표현이며, 이는 이별을 받아들이고 싶지 않은 마음을 역설적으로 드러낸 것이다.",
     "parentNote": "",
     "note": "",
     "해설": "화자는 지금도 지속되는 이별을 인정하지 못하고 ‘먼 후일’이라는 미래를 설정한 뒤, 그때 가서 ‘잊었노라’ 말하겠다고 한다. 그러나 그 미래에도 결코 잊지 못할 임이기에 ‘잊었노라’는 반어적 표현이며, 이는 이별을 받아들이고 싶지 않은 마음을 역설적으로 드러낸 것이다.",
     "answer": "",
     "label": "3번"
    },
    {
     "no": 4,
     "id": "G1-4",
     "three": false,
     "wr": null,
     "area": "고대가요",
     "type": "",
     "source": "2012년 고1 9월 학평",
     "in_typebook": false,
     "coreElement": "",
     "weakness1": "고대가요 세트의 감상·분석 문항입니다. 틀렸다면 아래 해설로 작품 해석을 다시 확인하세요.",
     "weakness2": "",
     "remediation": "㉠은 이별이 가져온 ‘고통’을 형상화한 부분이다. 임을 향한 화자의 애정이 식거나 변하고 있음을 나타내는 것이 아니라, 오히려 변함없는 애정 때문에 깊어지는 고통을 드러낸 것이므로 ‘애정의 변화’로 읽는 것은 적절하지 않다.",
     "parentNote": "",
     "note": "",
     "해설": "㉠은 이별이 가져온 ‘고통’을 형상화한 부분이다. 임을 향한 화자의 애정이 식거나 변하고 있음을 나타내는 것이 아니라, 오히려 변함없는 애정 때문에 깊어지는 고통을 드러낸 것이므로 ‘애정의 변화’로 읽는 것은 적절하지 않다.",
     "answer": "",
     "label": "4번"
    },
    {
     "no": 5,
     "id": "G1-5",
     "three": false,
     "wr": null,
     "area": "고대가요",
     "type": "",
     "source": "2012년 고1 9월 학평",
     "in_typebook": false,
     "coreElement": "",
     "weakness1": "고대가요 세트의 감상·분석 문항입니다. 틀렸다면 아래 해설로 작품 해석을 다시 확인하세요.",
     "weakness2": "",
     "remediation": "‘반달’은 견우와 직녀가 일 년에 한 번 만나는 칠월 칠석을 환기하여 만남에 대한 염원을 담고, ‘달님’은 행상 떠난 남편이 무사히 돌아올 수 있도록 길을 비추어 주는 매개자(媒介者)를 뜻한다. 두 시어 모두 임과의 재회를 바라는 화자의 마음과 연결된다.",
     "parentNote": "",
     "note": "",
     "해설": "‘반달’은 견우와 직녀가 일 년에 한 번 만나는 칠월 칠석을 환기하여 만남에 대한 염원을 담고, ‘달님’은 행상 떠난 남편이 무사히 돌아올 수 있도록 길을 비추어 주는 매개자(媒介者)를 뜻한다. 두 시어 모두 임과의 재회를 바라는 화자의 마음과 연결된다.",
     "answer": "",
     "label": "5번"
    },
    {
     "no": 6,
     "id": "G1-6",
     "three": false,
     "wr": null,
     "area": "고대가요",
     "type": "",
     "source": "2012년 고1 9월 학평",
     "in_typebook": false,
     "coreElement": "",
     "weakness1": "고대가요 세트의 감상·분석 문항입니다. 틀렸다면 아래 해설로 작품 해석을 다시 확인하세요.",
     "weakness2": "",
     "remediation": "ⓔ는 해가 저물어 남편이 집에 돌아오지 못하게 될까 봐 두려워하는 마음을 담은 표현이다. 이는 멀리 행상 나간 남편이 탈 없이 돌아오기를 바라는 아내의 간절한 소망(무사 귀환에 대한 염원)으로 읽어야 한다.",
     "parentNote": "",
     "note": "",
     "해설": "ⓔ는 해가 저물어 남편이 집에 돌아오지 못하게 될까 봐 두려워하는 마음을 담은 표현이다. 이는 멀리 행상 나간 남편이 탈 없이 돌아오기를 바라는 아내의 간절한 소망(무사 귀환에 대한 염원)으로 읽어야 한다.",
     "answer": "",
     "label": "6번"
    }
   ]
  },
  {
   "key": "s2",
   "title": "워크북(소책자) · 공무도하가",
   "range": "소책자 · 공무도하가",
   "questions": [
    {
     "no": 7,
     "id": "G1-7",
     "three": false,
     "wr": null,
     "area": "고대가요",
     "type": "",
     "source": "워크북 · 공무도하가",
     "in_typebook": false,
     "coreElement": "",
     "weakness1": "워크북(소책자) 고대가요 문항입니다. 틀렸다면 아래 해설로 작품 해석을 다시 확인하세요.",
     "weakness2": "",
     "remediation": "(가)는 『해동역사』에 4구체 한역시가로 기록되어 전해지는 고조선의 노래로, 이른 시기의 서정시가이다. 화자는 임을 부르며 물을 건너지 말 것을 애원하지만, 임은 결국 물에 빠져 죽고 화자는 슬픔, 안타까움, 체념의 정서를 느낀다. 구전되다가 한역되어 전해지며, ‘백수광부의 처’가 지은 개인적 작품이다.",
     "parentNote": "",
     "note": "",
     "해설": "(가)는 『해동역사』에 4구체 한역시가로 기록되어 전해지는 고조선의 노래로, 이른 시기의 서정시가이다. 화자는 임을 부르며 물을 건너지 말 것을 애원하지만, 임은 결국 물에 빠져 죽고 화자는 슬픔, 안타까움, 체념의 정서를 느낀다. 구전되다가 한역되어 전해지며, ‘백수광부의 처’가 지은 개인적 작품이다.",
     "answer": "",
     "label": "1번"
    },
    {
     "no": 8,
     "id": "G1-8",
     "three": false,
     "wr": null,
     "area": "고대가요",
     "type": "",
     "source": "워크북 · 공무도하가",
     "in_typebook": false,
     "coreElement": "",
     "weakness1": "워크북(소책자) 고대가요 문항입니다. 틀렸다면 아래 해설로 작품 해석을 다시 확인하세요.",
     "weakness2": "",
     "remediation": "(가)에서는 슬픔, 안타까움, 절망, 체념의 정서가 드러난다. 정처 없이 떠돌아야 하는 나그네의 불확실함이 드러난다. 죽은 아이를 그리워하며 슬퍼한다. ‘부서진 이름’, ‘공중에 헤어진 이름’, ‘주인 없는 이름’에서 이름의 주인이 이 세상을 떠난 것을 알 수 있고, 화자는 그 이름을 애타게 부르며 ‘내가 죽을 이름이여!’라고 슬픔을 격정적으로 드러낸다. ‘그대 하늘 끝 호올로 가신 임아’를 통해 임의 죽음을 알 수 있고, ‘귀촉도’에 화자의 감정을 이입하여 슬픔을 드러낸다. 혈육의 죽음을 슬퍼하며 관에 흙을 뿌리며 이별 인사하고 있다.",
     "parentNote": "",
     "note": "",
     "해설": "(가)에서는 슬픔, 안타까움, 절망, 체념의 정서가 드러난다. 정처 없이 떠돌아야 하는 나그네의 불확실함이 드러난다. 죽은 아이를 그리워하며 슬퍼한다. ‘부서진 이름’, ‘공중에 헤어진 이름’, ‘주인 없는 이름’에서 이름의 주인이 이 세상을 떠난 것을 알 수 있고, 화자는 그 이름을 애타게 부르며 ‘내가 죽을 이름이여!’라고 슬픔을 격정적으로 드러낸다. ‘그대 하늘 끝 호올로 가신 임아’를 통해 임의 죽음을 알 수 있고, ‘귀촉도’에 화자의 감정을 이입하여 슬픔을 드러낸다. 혈육의 죽음을 슬퍼하며 관에 흙을 뿌리며 이별 인사하고 있다.",
     "answer": "",
     "label": "2번"
    },
    {
     "no": 9,
     "id": "G1-9",
     "three": false,
     "wr": null,
     "area": "고대가요",
     "type": "",
     "source": "워크북 · 공무도하가",
     "in_typebook": false,
     "coreElement": "",
     "weakness1": "워크북(소책자) 고대가요 문항입니다. 틀렸다면 아래 해설로 작품 해석을 다시 확인하세요.",
     "weakness2": "",
     "remediation": "(가)의 물의 상징적 의미는 적절하다. 다만, <보기>에서 ‘물’은 이별을 의미하며 사별로 인한 것이 아니다. (가)는 화자의 정서가 애원-안타까움-슬픔-절망으로 변한다. <보기>는 이별의 상황에서 화자의 슬픔을 드러내며 정서 변화는 드러나지 않는다. <보기>의 자연은 ‘풀빛이 짙어지’는 생명력 넘치는 모습이나, 화자는 ‘남포에서 임 보내니 슬픈 노래가 일렁’이는 상황으로 자연과 대조적이다. (가)는 화자가 임을 만류하나 임이 듣지 않고 물에 휩쓸려 죽는 시간적 순서가 드러나고, (나)는 1, 2구의 자연과 인간의 정서가 교차된다. <보기>는 ‘남포’라는 이별의 구체적 공간이 제시된다.",
     "parentNote": "",
     "note": "",
     "해설": "(가)의 물의 상징적 의미는 적절하다. 다만, <보기>에서 ‘물’은 이별을 의미하며 사별로 인한 것이 아니다. (가)는 화자의 정서가 애원-안타까움-슬픔-절망으로 변한다. <보기>는 이별의 상황에서 화자의 슬픔을 드러내며 정서 변화는 드러나지 않는다. <보기>의 자연은 ‘풀빛이 짙어지’는 생명력 넘치는 모습이나, 화자는 ‘남포에서 임 보내니 슬픈 노래가 일렁’이는 상황으로 자연과 대조적이다. (가)는 화자가 임을 만류하나 임이 듣지 않고 물에 휩쓸려 죽는 시간적 순서가 드러나고, (나)는 1, 2구의 자연과 인간의 정서가 교차된다. <보기>는 ‘남포’라는 이별의 구체적 공간이 제시된다.",
     "answer": "",
     "label": "3번"
    },
    {
     "no": 10,
     "id": "G1-10",
     "three": false,
     "wr": null,
     "area": "고대가요",
     "type": "",
     "source": "워크북 · 공무도하가",
     "in_typebook": false,
     "coreElement": "",
     "weakness1": "워크북(소책자) 고대가요 문항입니다. 틀렸다면 아래 해설로 작품 해석을 다시 확인하세요.",
     "weakness2": "",
     "remediation": "[정답] 1구는 사랑, 2구는 이별, 3구는 죽음을 상징한다.  [해설] ‘물’의 원형적 상징이 사용되었다. 1구는 화자의 충만한 사랑을, 2구는 ‘물을 건너시네’를 통해 화자와 임 사이의 거리가 멀어졌으므로 이별을, 3구는 ‘물에 빠져 돌아가시니’라 하였으므로 죽음의 의미를 갖는다.",
     "parentNote": "",
     "note": "",
     "해설": "[정답] 1구는 사랑, 2구는 이별, 3구는 죽음을 상징한다.  [해설] ‘물’의 원형적 상징이 사용되었다. 1구는 화자의 충만한 사랑을, 2구는 ‘물을 건너시네’를 통해 화자와 임 사이의 거리가 멀어졌으므로 이별을, 3구는 ‘물에 빠져 돌아가시니’라 하였으므로 죽음의 의미를 갖는다.",
     "answer": "",
     "label": "4번"
    },
    {
     "no": 11,
     "id": "G1-11",
     "three": false,
     "wr": null,
     "area": "고대가요",
     "type": "",
     "source": "워크북 · 공무도하가",
     "in_typebook": false,
     "coreElement": "",
     "weakness1": "워크북(소책자) 고대가요 문항입니다. 틀렸다면 아래 해설로 작품 해석을 다시 확인하세요.",
     "weakness2": "",
     "remediation": "1구의 ‘물’은 화자의 충만한 사랑, 2구의 ‘물’은 이별, 3구의 ‘물’은 죽음을 상징한다. 도치법이 사용되지 않았고, 4구에서는 설의법을 사용하여 화자의 슬픔, 안타까움, 체념의 정서를 복합적으로 드러낸다. 선경후정으로 전개되지 않고, 화자의 정서 변화에 따라 시가 전개된다.",
     "parentNote": "",
     "note": "",
     "해설": "1구의 ‘물’은 화자의 충만한 사랑, 2구의 ‘물’은 이별, 3구의 ‘물’은 죽음을 상징한다. 도치법이 사용되지 않았고, 4구에서는 설의법을 사용하여 화자의 슬픔, 안타까움, 체념의 정서를 복합적으로 드러낸다. 선경후정으로 전개되지 않고, 화자의 정서 변화에 따라 시가 전개된다.",
     "answer": "",
     "label": "5번"
    },
    {
     "no": 12,
     "id": "G1-12",
     "three": false,
     "wr": null,
     "area": "고대가요",
     "type": "",
     "source": "워크북 · 공무도하가",
     "in_typebook": false,
     "coreElement": "",
     "weakness1": "워크북(소책자) 고대가요 문항입니다. 틀렸다면 아래 해설로 작품 해석을 다시 확인하세요.",
     "weakness2": "",
     "remediation": "‘꽃’을 뿌리며 나라 안에 일어난 변괴를 해결하고자 하는 주술적 성격을 드러낸다. ‘나 보기가 역겨워 가실 때’라는 화자가 원하지 않는 이별 상황을 가정하고, 임이 원하는 대로 이별을 하겠다는 희생적 태도를 드러낸다. ‘가시겠습니까’를 반복하여 이별에 대한 화자의 안타까움을 강조한다. ‘보내고 그리는 정’을 통해 사랑하는 사람을 붙잡지 않고 헤어지고서 그리워함을 알 수 있다. 임과 이별하기보다 자신의 생업을 버려두고서라도 임을 따르겠다는, 이별을 거부하는 적극적 태도가 드러난다.",
     "parentNote": "",
     "note": "",
     "해설": "‘꽃’을 뿌리며 나라 안에 일어난 변괴를 해결하고자 하는 주술적 성격을 드러낸다. ‘나 보기가 역겨워 가실 때’라는 화자가 원하지 않는 이별 상황을 가정하고, 임이 원하는 대로 이별을 하겠다는 희생적 태도를 드러낸다. ‘가시겠습니까’를 반복하여 이별에 대한 화자의 안타까움을 강조한다. ‘보내고 그리는 정’을 통해 사랑하는 사람을 붙잡지 않고 헤어지고서 그리워함을 알 수 있다. 임과 이별하기보다 자신의 생업을 버려두고서라도 임을 따르겠다는, 이별을 거부하는 적극적 태도가 드러난다.",
     "answer": "",
     "label": "6번"
    },
    {
     "no": 13,
     "id": "G1-13",
     "three": false,
     "wr": null,
     "area": "고대가요",
     "type": "",
     "source": "워크북 · 공무도하가",
     "in_typebook": false,
     "coreElement": "",
     "weakness1": "워크북(소책자) 고대가요 문항입니다. 틀렸다면 아래 해설로 작품 해석을 다시 확인하세요.",
     "weakness2": "",
     "remediation": "작품의 최초 작가는 백수광부의 아내이다. 공후를 타며 부른 노래란 의미로 ‘공후인’이라는 별칭이 있다. ‘물’은 기에서 ‘사랑’을, 승에서 ‘이별’을, 전에서 ‘죽음’을 상징한다.",
     "parentNote": "",
     "note": "",
     "해설": "작품의 최초 작가는 백수광부의 아내이다. 공후를 타며 부른 노래란 의미로 ‘공후인’이라는 별칭이 있다. ‘물’은 기에서 ‘사랑’을, 승에서 ‘이별’을, 전에서 ‘죽음’을 상징한다.",
     "answer": "",
     "label": "7번"
    },
    {
     "no": 14,
     "id": "G1-14",
     "three": false,
     "wr": null,
     "area": "고대가요",
     "type": "",
     "source": "워크북 · 공무도하가",
     "in_typebook": false,
     "coreElement": "",
     "weakness1": "워크북(소책자) 고대가요 문항입니다. 틀렸다면 아래 해설로 작품 해석을 다시 확인하세요.",
     "weakness2": "",
     "remediation": "[정답] 사랑, 이별, 죽음  [해설] 1행의 ‘물’은 화자가 임에게 건너지 말라고 애원하는 ‘사랑’을, 2행의 ‘물’은 임이 건너간 것으로 ‘이별’을, 3행의 ‘물’은 임이 빠져 죽었으므로 ‘죽음’을 상징한다.",
     "parentNote": "",
     "note": "",
     "해설": "[정답] 사랑, 이별, 죽음  [해설] 1행의 ‘물’은 화자가 임에게 건너지 말라고 애원하는 ‘사랑’을, 2행의 ‘물’은 임이 건너간 것으로 ‘이별’을, 3행의 ‘물’은 임이 빠져 죽었으므로 ‘죽음’을 상징한다.",
     "answer": "",
     "label": "8번"
    },
    {
     "no": 15,
     "id": "G1-15",
     "three": false,
     "wr": null,
     "area": "고대가요",
     "type": "",
     "source": "워크북 · 공무도하가",
     "in_typebook": false,
     "coreElement": "",
     "weakness1": "워크북(소책자) 고대가요 문항입니다. 틀렸다면 아래 해설로 작품 해석을 다시 확인하세요.",
     "weakness2": "",
     "remediation": "화자는 임에게 물을 건너지 말라고 애원하고, 물을 건너는 임을 보며 초조해하며 임과의 이별을 슬퍼하고, 임이 결국 물에 빠져 죽으니 체념한다.",
     "parentNote": "",
     "note": "",
     "해설": "화자는 임에게 물을 건너지 말라고 애원하고, 물을 건너는 임을 보며 초조해하며 임과의 이별을 슬퍼하고, 임이 결국 물에 빠져 죽으니 체념한다.",
     "answer": "",
     "label": "9번"
    },
    {
     "no": 16,
     "id": "G1-16",
     "three": false,
     "wr": null,
     "area": "고대가요",
     "type": "",
     "source": "워크북 · 공무도하가",
     "in_typebook": false,
     "coreElement": "",
     "weakness1": "워크북(소책자) 고대가요 문항입니다. 틀렸다면 아래 해설로 작품 해석을 다시 확인하세요.",
     "weakness2": "",
     "remediation": "‘물’은 임이 나를 떠나 건너는 강으로 이별, 슬픔, 단절을 상징하고, 이승과 저승을 가르는 경계, 삶과 죽음의 경계를 의미한다. ‘삼도천’은 죽은 사람이 건너는 강으로 산 사람과 죽은 사람을 나누는 경계이다.",
     "parentNote": "",
     "note": "",
     "해설": "‘물’은 임이 나를 떠나 건너는 강으로 이별, 슬픔, 단절을 상징하고, 이승과 저승을 가르는 경계, 삶과 죽음의 경계를 의미한다. ‘삼도천’은 죽은 사람이 건너는 강으로 산 사람과 죽은 사람을 나누는 경계이다.",
     "answer": "",
     "label": "10번"
    },
    {
     "no": 17,
     "id": "G1-17",
     "three": false,
     "wr": null,
     "area": "고대가요",
     "type": "",
     "source": "워크북 · 공무도하가",
     "in_typebook": false,
     "coreElement": "",
     "weakness1": "워크북(소책자) 고대가요 문항입니다. 틀렸다면 아래 해설로 작품 해석을 다시 확인하세요.",
     "weakness2": "",
     "remediation": "(가)는 화자의 독백체로 시상이 전개되며, 화자가 임을 만류하다가 임의 죽음을 체념하는 모습이 화자의 목소리로 드러난다. 따라서 대화를 활용하였다는 것은 적절하지 않다. ‘가신 임을 어찌할꼬’에 화자의 정서가 드러난다.",
     "parentNote": "",
     "note": "",
     "해설": "(가)는 화자의 독백체로 시상이 전개되며, 화자가 임을 만류하다가 임의 죽음을 체념하는 모습이 화자의 목소리로 드러난다. 따라서 대화를 활용하였다는 것은 적절하지 않다. ‘가신 임을 어찌할꼬’에 화자의 정서가 드러난다.",
     "answer": "",
     "label": "11번"
    },
    {
     "no": 18,
     "id": "G1-18",
     "three": false,
     "wr": null,
     "area": "고대가요",
     "type": "",
     "source": "워크북 · 공무도하가",
     "in_typebook": false,
     "coreElement": "",
     "weakness1": "워크북(소책자) 고대가요 문항입니다. 틀렸다면 아래 해설로 작품 해석을 다시 확인하세요.",
     "weakness2": "",
     "remediation": "(가)는 집단 가요에서 개인적 서정시로의 과도기적 작품이라고 할 수 있다.",
     "parentNote": "",
     "note": "",
     "해설": "(가)는 집단 가요에서 개인적 서정시로의 과도기적 작품이라고 할 수 있다.",
     "answer": "",
     "label": "12번"
    },
    {
     "no": 19,
     "id": "G1-19",
     "three": false,
     "wr": null,
     "area": "고대가요",
     "type": "",
     "source": "워크북 · 공무도하가",
     "in_typebook": false,
     "coreElement": "",
     "weakness1": "워크북(소책자) 고대가요 문항입니다. 틀렸다면 아래 해설로 작품 해석을 다시 확인하세요.",
     "weakness2": "",
     "remediation": "㉠은 이별을 상징하는 것으로 볼 수 있다. (선지 분석) 사랑을 더욱 깊게 하는 이별 / 화자의 순수한 마음 / 부정적인 현실 / 이상적 존재 / 삶의 비애.",
     "parentNote": "",
     "note": "",
     "해설": "㉠은 이별을 상징하는 것으로 볼 수 있다. (선지 분석) 사랑을 더욱 깊게 하는 이별 / 화자의 순수한 마음 / 부정적인 현실 / 이상적 존재 / 삶의 비애.",
     "answer": "",
     "label": "13번"
    },
    {
     "no": 20,
     "id": "G1-20",
     "three": false,
     "wr": null,
     "area": "고대가요",
     "type": "",
     "source": "워크북 · 공무도하가",
     "in_typebook": false,
     "coreElement": "",
     "weakness1": "워크북(소책자) 고대가요 문항입니다. 틀렸다면 아래 해설로 작품 해석을 다시 확인하세요.",
     "weakness2": "",
     "remediation": "‘가신 임을 어찌할꼬’에서 ‘백수 광부의 아내’는 ‘백수 광부’의 죽음을 어찌할 수 없는 일로 받아들이며 체념하는 태도를 보인다. 따라서 슬픔을 극복하려는 의지를 보인다고 볼 수 없다.",
     "parentNote": "",
     "note": "",
     "해설": "‘가신 임을 어찌할꼬’에서 ‘백수 광부의 아내’는 ‘백수 광부’의 죽음을 어찌할 수 없는 일로 받아들이며 체념하는 태도를 보인다. 따라서 슬픔을 극복하려는 의지를 보인다고 볼 수 없다.",
     "answer": "",
     "label": "14번"
    },
    {
     "no": 21,
     "id": "G1-21",
     "three": false,
     "wr": null,
     "area": "고대가요",
     "type": "",
     "source": "워크북 · 공무도하가",
     "in_typebook": false,
     "coreElement": "",
     "weakness1": "워크북(소책자) 고대가요 문항입니다. 틀렸다면 아래 해설로 작품 해석을 다시 확인하세요.",
     "weakness2": "",
     "remediation": "‘물’은 임을 죽게 만들어 화자와 임을 이별하게 하므로, 인연이 끝난 후 회복의 가능성을 암시한다고 볼 수 없다.",
     "parentNote": "",
     "note": "",
     "해설": "‘물’은 임을 죽게 만들어 화자와 임을 이별하게 하므로, 인연이 끝난 후 회복의 가능성을 암시한다고 볼 수 없다.",
     "answer": "",
     "label": "15번"
    },
    {
     "no": 22,
     "id": "G1-22",
     "three": false,
     "wr": null,
     "area": "고대가요",
     "type": "",
     "source": "워크북 · 공무도하가",
     "in_typebook": false,
     "coreElement": "",
     "weakness1": "워크북(소책자) 고대가요 문항입니다. 틀렸다면 아래 해설로 작품 해석을 다시 확인하세요.",
     "weakness2": "",
     "remediation": "(가)의 화자는 임이 물을 건너는 것을 만류한다. 화자가 있는 쪽은 이승, ‘물’은 저승·죽음의 세계를 의미하기 때문이다. <보기>의 아내는 ‘이쪽 동네’라고 표현하며 ‘저쪽 동네’와 구분 짓고, 이사 온 아파트에서 중산층의 삶에 편입되기를 희망한다.",
     "parentNote": "",
     "note": "",
     "해설": "(가)의 화자는 임이 물을 건너는 것을 만류한다. 화자가 있는 쪽은 이승, ‘물’은 저승·죽음의 세계를 의미하기 때문이다. <보기>의 아내는 ‘이쪽 동네’라고 표현하며 ‘저쪽 동네’와 구분 짓고, 이사 온 아파트에서 중산층의 삶에 편입되기를 희망한다.",
     "answer": "",
     "label": "16번"
    },
    {
     "no": 23,
     "id": "G1-23",
     "three": false,
     "wr": null,
     "area": "고대가요",
     "type": "",
     "source": "워크북 · 공무도하가",
     "in_typebook": false,
     "coreElement": "",
     "weakness1": "워크북(소책자) 고대가요 문항입니다. 틀렸다면 아래 해설로 작품 해석을 다시 확인하세요.",
     "weakness2": "",
     "remediation": "ㄴ. 노래의 작가를 ‘백수광부의 아내’로 보면 작가와 시적 화자가 일치하고, ‘곽리자고의 아내’로 보면 일치하지 않는 경우로 볼 수 있으나, 누구를 작가로 보느냐에 따라 작품의 주제와 정서가 바뀌지는 않으므로 시적 대상이 불분명해진다는 감상은 적절하지 않다. ㄹ. ‘강’을 중심으로 임과 화자의 삶과 죽음이 엇갈린다고 볼 수 있고, 배경 설화를 참고하면 아내가 남편을 따라 물에 몸을 던져 죽은 것은 물을 통해 남편과 아내의 영원한 사랑이 이루어진 것, 즉 죽음으로 끝나지 않고 만남과 재생의 의미까지 내포한다고도 볼 수 있다.",
     "parentNote": "",
     "note": "",
     "해설": "ㄴ. 노래의 작가를 ‘백수광부의 아내’로 보면 작가와 시적 화자가 일치하고, ‘곽리자고의 아내’로 보면 일치하지 않는 경우로 볼 수 있으나, 누구를 작가로 보느냐에 따라 작품의 주제와 정서가 바뀌지는 않으므로 시적 대상이 불분명해진다는 감상은 적절하지 않다. ㄹ. ‘강’을 중심으로 임과 화자의 삶과 죽음이 엇갈린다고 볼 수 있고, 배경 설화를 참고하면 아내가 남편을 따라 물에 몸을 던져 죽은 것은 물을 통해 남편과 아내의 영원한 사랑이 이루어진 것, 즉 죽음으로 끝나지 않고 만남과 재생의 의미까지 내포한다고도 볼 수 있다.",
     "answer": "",
     "label": "17번"
    },
    {
     "no": 24,
     "id": "G1-24",
     "three": false,
     "wr": null,
     "area": "고대가요",
     "type": "",
     "source": "워크북 · 공무도하가",
     "in_typebook": false,
     "coreElement": "",
     "weakness1": "워크북(소책자) 고대가요 문항입니다. 틀렸다면 아래 해설로 작품 해석을 다시 확인하세요.",
     "weakness2": "",
     "remediation": "㉠은 사랑, ㉡은 이별, ㉢은 임의 죽음, ⓐ는 임과의 이별과 그로 인한 화자의 슬픔·눈물 등을 상징한다. 학생1: ㉠은 임을 만류하는 화자의 사랑이 담겨 있으나 ⓐ가 임의 사랑을 의미하지 않는다. 학생4: ㉠과 ⓐ는 임의 눈물을 상징하는 것이 아니다. 학생5: ㉠~㉢은 ‘물’의 의미 변화를 통해 사랑의 허무함을 극복한다고 할 수 없다. 화자는 ‘가신 임을 어찌할꼬’라며 탄식과 체념의 정서를 드러낸다.",
     "parentNote": "",
     "note": "",
     "해설": "㉠은 사랑, ㉡은 이별, ㉢은 임의 죽음, ⓐ는 임과의 이별과 그로 인한 화자의 슬픔·눈물 등을 상징한다. 학생1: ㉠은 임을 만류하는 화자의 사랑이 담겨 있으나 ⓐ가 임의 사랑을 의미하지 않는다. 학생4: ㉠과 ⓐ는 임의 눈물을 상징하는 것이 아니다. 학생5: ㉠~㉢은 ‘물’의 의미 변화를 통해 사랑의 허무함을 극복한다고 할 수 없다. 화자는 ‘가신 임을 어찌할꼬’라며 탄식과 체념의 정서를 드러낸다.",
     "answer": "",
     "label": "18번"
    },
    {
     "no": 25,
     "id": "G1-25",
     "three": false,
     "wr": null,
     "area": "고대가요",
     "type": "",
     "source": "워크북 · 공무도하가",
     "in_typebook": false,
     "coreElement": "",
     "weakness1": "워크북(소책자) 고대가요 문항입니다. 틀렸다면 아래 해설로 작품 해석을 다시 확인하세요.",
     "weakness2": "",
     "remediation": "(가)는 백수 광부가 강을 건너다 빠져 죽자 아내가 슬퍼하며 지어 불렀다는 노래로 우리 민족의 전통적 정서인 ‘한(恨)의 정서’를 담고 있다. ‘물’에는 이별, 슬픔, 단절, 사랑 등이 담겨 있다. ‘가신 임을 어찌할꼬’에서 설의적 어투로 화자의 슬픔과 체념을 드러낸다. 1, 2행은 근심·걱정·불안·초조가, 3, 4행은 체념·안타까움·절망·한탄이 담겨 있다. 내적 성장의 계기를 마련하고 있다고 볼 수 없다.",
     "parentNote": "",
     "note": "",
     "해설": "(가)는 백수 광부가 강을 건너다 빠져 죽자 아내가 슬퍼하며 지어 불렀다는 노래로 우리 민족의 전통적 정서인 ‘한(恨)의 정서’를 담고 있다. ‘물’에는 이별, 슬픔, 단절, 사랑 등이 담겨 있다. ‘가신 임을 어찌할꼬’에서 설의적 어투로 화자의 슬픔과 체념을 드러낸다. 1, 2행은 근심·걱정·불안·초조가, 3, 4행은 체념·안타까움·절망·한탄이 담겨 있다. 내적 성장의 계기를 마련하고 있다고 볼 수 없다.",
     "answer": "",
     "label": "19번"
    },
    {
     "no": 26,
     "id": "G1-26",
     "three": false,
     "wr": null,
     "area": "고대가요",
     "type": "",
     "source": "워크북 · 공무도하가",
     "in_typebook": false,
     "coreElement": "",
     "weakness1": "워크북(소책자) 고대가요 문항입니다. 틀렸다면 아래 해설로 작품 해석을 다시 확인하세요.",
     "weakness2": "",
     "remediation": "[정답] 집단적·제의적 성격의 고대가요와 달리, (가)는 개인적·서정적 성격의 서정시가의 출현이라는 문학사적 가치를 지닌다.  [해설] ㉮는 왕의 강림을 기원하며 여러 사람이 흙을 파면서 노래를 부르니 하늘에서 알이 내려오고, 그 알을 깨고 나온 사람이 왕이 되었다고 한다. ㉮는 집단적·주술적 성격을 갖는 이른 시기 노래의 특징을 보여 준다. 그러나 (가)는 ‘백수 광부의 아내’가 남편의 죽음에서 느끼는 슬픔을 드러내므로 개인적·서정적 특징을 보여 준다. 이처럼 고대가요는 초기의 서사적·집단적 성격에서 점차 서정적·개인적 성격으로 바뀌어 갔다.",
     "parentNote": "",
     "note": "",
     "해설": "[정답] 집단적·제의적 성격의 고대가요와 달리, (가)는 개인적·서정적 성격의 서정시가의 출현이라는 문학사적 가치를 지닌다.  [해설] ㉮는 왕의 강림을 기원하며 여러 사람이 흙을 파면서 노래를 부르니 하늘에서 알이 내려오고, 그 알을 깨고 나온 사람이 왕이 되었다고 한다. ㉮는 집단적·주술적 성격을 갖는 이른 시기 노래의 특징을 보여 준다. 그러나 (가)는 ‘백수 광부의 아내’가 남편의 죽음에서 느끼는 슬픔을 드러내므로 개인적·서정적 특징을 보여 준다. 이처럼 고대가요는 초기의 서사적·집단적 성격에서 점차 서정적·개인적 성격으로 바뀌어 갔다.",
     "answer": "",
     "label": "20번"
    },
    {
     "no": 27,
     "id": "G1-27",
     "three": false,
     "wr": null,
     "area": "고대가요",
     "type": "",
     "source": "워크북 · 공무도하가",
     "in_typebook": false,
     "coreElement": "",
     "weakness1": "워크북(소책자) 고대가요 문항입니다. 틀렸다면 아래 해설로 작품 해석을 다시 확인하세요.",
     "weakness2": "",
     "remediation": "(가)는 광인의 아내가 남편과의 이별의 슬픔을 노래한 작품이며, 곽리자고는 광인의 아내가 부른 노래를 전한 것이므로 곽리자고를 창작 동기의 주체로 보는 선지는 적절하지 않다.",
     "parentNote": "",
     "note": "",
     "해설": "(가)는 광인의 아내가 남편과의 이별의 슬픔을 노래한 작품이며, 곽리자고는 광인의 아내가 부른 노래를 전한 것이므로 곽리자고를 창작 동기의 주체로 보는 선지는 적절하지 않다.",
     "answer": "",
     "label": "21번"
    },
    {
     "no": 28,
     "id": "G1-28",
     "three": false,
     "wr": null,
     "area": "고대가요",
     "type": "",
     "source": "워크북 · 공무도하가",
     "in_typebook": false,
     "coreElement": "",
     "weakness1": "워크북(소책자) 고대가요 문항입니다. 틀렸다면 아래 해설로 작품 해석을 다시 확인하세요.",
     "weakness2": "",
     "remediation": "(가)의 화자는 물을 건넌 임의 죽음으로 이별의 슬픔을 느끼고, 이러한 이별의 정한은 우리 민족의 보편적 정서로 후대 시가에 이어졌다. 비유적으로 정서를 표현하고 있지 않다. ‘임’이 동경과 희망을 품었는지 알 수 없다. ‘물’을 건너면 새로운 세상이 열리는지 알 수 없으며, 이 작품에서 ‘물’은 사랑·이별·슬픔 등의 의미를 지닌다. 화자의 소망을 설의적으로 드러내는 부분은 없다. ‘가신 임을 어이할꼬’라며 임의 죽음으로 인한 탄식과 체념을 드러낸다.",
     "parentNote": "",
     "note": "",
     "해설": "(가)의 화자는 물을 건넌 임의 죽음으로 이별의 슬픔을 느끼고, 이러한 이별의 정한은 우리 민족의 보편적 정서로 후대 시가에 이어졌다. 비유적으로 정서를 표현하고 있지 않다. ‘임’이 동경과 희망을 품었는지 알 수 없다. ‘물’을 건너면 새로운 세상이 열리는지 알 수 없으며, 이 작품에서 ‘물’은 사랑·이별·슬픔 등의 의미를 지닌다. 화자의 소망을 설의적으로 드러내는 부분은 없다. ‘가신 임을 어이할꼬’라며 임의 죽음으로 인한 탄식과 체념을 드러낸다.",
     "answer": "",
     "label": "22번"
    }
   ]
  },
  {
   "key": "s3",
   "title": "워크북(소책자) · 황조가",
   "range": "소책자 · 황조가",
   "questions": [
    {
     "no": 29,
     "id": "G1-29",
     "three": false,
     "wr": null,
     "area": "고대가요",
     "type": "",
     "source": "워크북 · 황조가",
     "in_typebook": false,
     "coreElement": "",
     "weakness1": "워크북(소책자) 고대가요 문항입니다. 틀렸다면 아래 해설로 작품 해석을 다시 확인하세요.",
     "weakness2": "",
     "remediation": "(가)의 화자는 ‘외로워라 이 내 몸은’에서 ‘외롭다’는 정서를 직접적으로 드러낸다. 함께 돌아갈 이가 없다는 데에서 오는 고독감을 드러낸다. 고대 가요이자 개인의 정서를 노래한 서정 가요이다. 암수가 정다운 꾀꼬리(자연물)를 먼저 제시한 후 이와 대조적인 화자의 처지를 드러낸다. ‘꾀꼬리’는 화자의 처지와 대조적인 객관적 상관물로, 화자의 외롭고 슬픈 심정을 부각한다.",
     "parentNote": "",
     "note": "",
     "해설": "(가)의 화자는 ‘외로워라 이 내 몸은’에서 ‘외롭다’는 정서를 직접적으로 드러낸다. 함께 돌아갈 이가 없다는 데에서 오는 고독감을 드러낸다. 고대 가요이자 개인의 정서를 노래한 서정 가요이다. 암수가 정다운 꾀꼬리(자연물)를 먼저 제시한 후 이와 대조적인 화자의 처지를 드러낸다. ‘꾀꼬리’는 화자의 처지와 대조적인 객관적 상관물로, 화자의 외롭고 슬픈 심정을 부각한다.",
     "answer": "",
     "label": "23번"
    },
    {
     "no": 30,
     "id": "G1-30",
     "three": false,
     "wr": null,
     "area": "고대가요",
     "type": "",
     "source": "워크북 · 황조가",
     "in_typebook": false,
     "coreElement": "",
     "weakness1": "워크북(소책자) 고대가요 문항입니다. 틀렸다면 아래 해설로 작품 해석을 다시 확인하세요.",
     "weakness2": "",
     "remediation": "‘꾀꼬리’는 객관적 상관물로 ‘암수 정답게 노니는’ 존재이다. 이러한 꾀꼬리의 모습은 홀로 돌아가는 화자의 처지와 대비되어 화자의 쓸쓸하고 고독한 심리를 더욱 강조한다.",
     "parentNote": "",
     "note": "",
     "해설": "‘꾀꼬리’는 객관적 상관물로 ‘암수 정답게 노니는’ 존재이다. 이러한 꾀꼬리의 모습은 홀로 돌아가는 화자의 처지와 대비되어 화자의 쓸쓸하고 고독한 심리를 더욱 강조한다.",
     "answer": "",
     "label": "24번"
    },
    {
     "no": 31,
     "id": "G1-31",
     "three": false,
     "wr": null,
     "area": "고대가요",
     "type": "",
     "source": "워크북 · 황조가",
     "in_typebook": false,
     "coreElement": "",
     "weakness1": "워크북(소책자) 고대가요 문항입니다. 틀렸다면 아래 해설로 작품 해석을 다시 확인하세요.",
     "weakness2": "",
     "remediation": "[정답] ‘꾀꼬리’는 임을 잃은 화자의 슬픔과 외로움, 상실감을 강조하여 나타낸다.  [해설] 화자는 암수가 서로 정다운 꾀꼬리를 보고, 임과 이별한 자신의 슬픔과 외로움을 더욱 강하게 느낀다. 따라서 꾀꼬리는 화자의 감정을 강조하는 객관적 상관물이다.",
     "parentNote": "",
     "note": "",
     "해설": "[정답] ‘꾀꼬리’는 임을 잃은 화자의 슬픔과 외로움, 상실감을 강조하여 나타낸다.  [해설] 화자는 암수가 서로 정다운 꾀꼬리를 보고, 임과 이별한 자신의 슬픔과 외로움을 더욱 강하게 느낀다. 따라서 꾀꼬리는 화자의 감정을 강조하는 객관적 상관물이다.",
     "answer": "",
     "label": "25번"
    },
    {
     "no": 32,
     "id": "G1-32",
     "three": false,
     "wr": null,
     "area": "고대가요",
     "type": "",
     "source": "워크북 · 황조가",
     "in_typebook": false,
     "coreElement": "",
     "weakness1": "워크북(소책자) 고대가요 문항입니다. 틀렸다면 아래 해설로 작품 해석을 다시 확인하세요.",
     "weakness2": "",
     "remediation": "㉠은 화자의 처지와 대조되어 화자의 외로움을 부각하는 객관적 상관물이다. ‘나릿믈’은 ‘어져 녹져’ 하지만 화자는 ‘올로’ 지내므로 자연물과 화자의 처지가 대조되어 외로움이 부각되는 객관적 상관물이다. ‘묏버들’은 화자의 분신이며 임이 자신을 잊지 않기를 바라는 마음을 전달하는 소재이다. ‘벌레’는 ‘부끄러운 이름을 슬퍼하는 까닭입니다’라 하였으므로 화자의 정서가 투영된 대상이다. ‘가을 밤’·‘실솔’이 우는 것은 쓸쓸한 분위기를 형성해 외로움을 심화시키는 배경이다. ‘자규’는 봄밤에 울고 화자도 잠들지 못하므로 화자와 정서가 같다.",
     "parentNote": "",
     "note": "",
     "해설": "㉠은 화자의 처지와 대조되어 화자의 외로움을 부각하는 객관적 상관물이다. ‘나릿믈’은 ‘어져 녹져’ 하지만 화자는 ‘올로’ 지내므로 자연물과 화자의 처지가 대조되어 외로움이 부각되는 객관적 상관물이다. ‘묏버들’은 화자의 분신이며 임이 자신을 잊지 않기를 바라는 마음을 전달하는 소재이다. ‘벌레’는 ‘부끄러운 이름을 슬퍼하는 까닭입니다’라 하였으므로 화자의 정서가 투영된 대상이다. ‘가을 밤’·‘실솔’이 우는 것은 쓸쓸한 분위기를 형성해 외로움을 심화시키는 배경이다. ‘자규’는 봄밤에 울고 화자도 잠들지 못하므로 화자와 정서가 같다.",
     "answer": "",
     "label": "26번"
    },
    {
     "no": 33,
     "id": "G1-33",
     "three": false,
     "wr": null,
     "area": "고대가요",
     "type": "",
     "source": "워크북 · 황조가",
     "in_typebook": false,
     "coreElement": "",
     "weakness1": "워크북(소책자) 고대가요 문항입니다. 틀렸다면 아래 해설로 작품 해석을 다시 확인하세요.",
     "weakness2": "",
     "remediation": "[정답] (1) 화자의 정서를 간접적으로 드러내는 소재는 객관적 상관물이다. (2) (가)의 객관적 상관물은 ‘꾀꼬리’, <보기>의 객관적 상관물은 ‘시내’이다. (3) (가)에서는 ‘꾀꼬리’의 정다운 모습을 통해 화자의 고독하고 슬픈 정서를 심화시키고, <보기>에서는 밤낮으로 울며 흐르는 ‘시내’에 화자의 감정을 이입하여 임을 향해 쉬지 않고 울며 지내는 정서를 드러낸다.  [해설] (가)와 <보기>는 화자의 정서를 객관적 상관물을 통해 드러내는데, (가)의 정서는 객관적 상관물인 ‘꾀꼬리’와 상반되며, <보기>의 화자는 ‘시내’를 의인화하여 자신의 슬픈 감정을 이입해 드러낸다.",
     "parentNote": "",
     "note": "",
     "해설": "[정답] (1) 화자의 정서를 간접적으로 드러내는 소재는 객관적 상관물이다. (2) (가)의 객관적 상관물은 ‘꾀꼬리’, <보기>의 객관적 상관물은 ‘시내’이다. (3) (가)에서는 ‘꾀꼬리’의 정다운 모습을 통해 화자의 고독하고 슬픈 정서를 심화시키고, <보기>에서는 밤낮으로 울며 흐르는 ‘시내’에 화자의 감정을 이입하여 임을 향해 쉬지 않고 울며 지내는 정서를 드러낸다.  [해설] (가)와 <보기>는 화자의 정서를 객관적 상관물을 통해 드러내는데, (가)의 정서는 객관적 상관물인 ‘꾀꼬리’와 상반되며, <보기>의 화자는 ‘시내’를 의인화하여 자신의 슬픈 감정을 이입해 드러낸다.",
     "answer": "",
     "label": "27번"
    },
    {
     "no": 34,
     "id": "G1-34",
     "three": false,
     "wr": null,
     "area": "고대가요",
     "type": "",
     "source": "워크북 · 황조가",
     "in_typebook": false,
     "coreElement": "",
     "weakness1": "워크북(소책자) 고대가요 문항입니다. 틀렸다면 아래 해설로 작품 해석을 다시 확인하세요.",
     "weakness2": "",
     "remediation": "선경후정은 한시에서 흔히 쓰이는 시상 전개 방식으로, 먼저 자연이나 사물을 묘사한 후 감정이나 생각을 읊는 방식이다. 이러한 방식이 사용된 것은 길재의 시조로, 초·중장에서 고려 왕조의 궁궐터인 만월대의 황폐해진 풍경을 묘사한 후 종장에서 고려의 패망을 안타까워하는 화자의 정서를 제시한다.",
     "parentNote": "",
     "note": "",
     "해설": "선경후정은 한시에서 흔히 쓰이는 시상 전개 방식으로, 먼저 자연이나 사물을 묘사한 후 감정이나 생각을 읊는 방식이다. 이러한 방식이 사용된 것은 길재의 시조로, 초·중장에서 고려 왕조의 궁궐터인 만월대의 황폐해진 풍경을 묘사한 후 종장에서 고려의 패망을 안타까워하는 화자의 정서를 제시한다.",
     "answer": "",
     "label": "28번"
    },
    {
     "no": 35,
     "id": "G1-35",
     "three": false,
     "wr": null,
     "area": "고대가요",
     "type": "",
     "source": "워크북 · 황조가",
     "in_typebook": false,
     "coreElement": "",
     "weakness1": "워크북(소책자) 고대가요 문항입니다. 틀렸다면 아래 해설로 작품 해석을 다시 확인하세요.",
     "weakness2": "",
     "remediation": "‘꾀꼬리’는 이별한 화자의 처지와 대조되어 슬픔을 부각하는 객관적 상관물이다. <보기>에서 ㉤은 화자의 외로운 처지를 부각하므로 ‘꾀꼬리’와 같은 객관적 상관물로 볼 수 있다. 나머지는 화자가 임의 소식을 알기 위해 가는 공간, 임을 비유한 것, 임과의 만남을 방해하는 존재 등이다.",
     "parentNote": "",
     "note": "",
     "해설": "‘꾀꼬리’는 이별한 화자의 처지와 대조되어 슬픔을 부각하는 객관적 상관물이다. <보기>에서 ㉤은 화자의 외로운 처지를 부각하므로 ‘꾀꼬리’와 같은 객관적 상관물로 볼 수 있다. 나머지는 화자가 임의 소식을 알기 위해 가는 공간, 임을 비유한 것, 임과의 만남을 방해하는 존재 등이다.",
     "answer": "",
     "label": "29번"
    },
    {
     "no": 36,
     "id": "G1-36",
     "three": false,
     "wr": null,
     "area": "고대가요",
     "type": "",
     "source": "워크북 · 황조가",
     "in_typebook": false,
     "coreElement": "",
     "weakness1": "워크북(소책자) 고대가요 문항입니다. 틀렸다면 아래 해설로 작품 해석을 다시 확인하세요.",
     "weakness2": "",
     "remediation": "(가) 황조가는 고구려 유리왕이 지은 것으로 알려진 작품으로, 『삼국사기』의 배경 설화 속에 4구체 한역시가 형태로 삽입되어 전승된다. 자연사와 인간사의 대조, 선경후정의 시상 전개를 통해 이별의 슬픔·개인적 고뇌를 표현한 서정시이다. 국가 행사나 노래를 불러 문제를 해결하려는 제의적·주술적 성격의 노래가 아니라 개인적·서정적 성격의 시가이다.",
     "parentNote": "",
     "note": "",
     "해설": "(가) 황조가는 고구려 유리왕이 지은 것으로 알려진 작품으로, 『삼국사기』의 배경 설화 속에 4구체 한역시가 형태로 삽입되어 전승된다. 자연사와 인간사의 대조, 선경후정의 시상 전개를 통해 이별의 슬픔·개인적 고뇌를 표현한 서정시이다. 국가 행사나 노래를 불러 문제를 해결하려는 제의적·주술적 성격의 노래가 아니라 개인적·서정적 성격의 시가이다.",
     "answer": "",
     "label": "30번"
    },
    {
     "no": 37,
     "id": "G1-37",
     "three": false,
     "wr": null,
     "area": "고대가요",
     "type": "",
     "source": "워크북 · 황조가",
     "in_typebook": false,
     "coreElement": "",
     "weakness1": "워크북(소책자) 고대가요 문항입니다. 틀렸다면 아래 해설로 작품 해석을 다시 확인하세요.",
     "weakness2": "",
     "remediation": "㉠‘꾀꼬리’는 화자의 상황과 대조되어 외로운 정서를 부각하는 객관적 상관물이다. 화자는 ‘근심 어린 외로운 잠자리’에 있고 ‘복숭아꽃은 근심 없어 봄바람에 웃고’ 있어 화자의 상황과 대조되므로 객관적 상관물이다. ‘약’은 임에게 바치는 사랑과 정성, ‘암소’는 헌화하는 노인의 신분을 알게 하는 소재, ‘잎’은 일찍 떨어져 이른 죽음을 맞은 누이의 비유, ‘달님’은 광명의 상징이자 기원의 대상이다.",
     "parentNote": "",
     "note": "",
     "해설": "㉠‘꾀꼬리’는 화자의 상황과 대조되어 외로운 정서를 부각하는 객관적 상관물이다. 화자는 ‘근심 어린 외로운 잠자리’에 있고 ‘복숭아꽃은 근심 없어 봄바람에 웃고’ 있어 화자의 상황과 대조되므로 객관적 상관물이다. ‘약’은 임에게 바치는 사랑과 정성, ‘암소’는 헌화하는 노인의 신분을 알게 하는 소재, ‘잎’은 일찍 떨어져 이른 죽음을 맞은 누이의 비유, ‘달님’은 광명의 상징이자 기원의 대상이다.",
     "answer": "",
     "label": "31번"
    },
    {
     "no": 38,
     "id": "G1-38",
     "three": false,
     "wr": null,
     "area": "고대가요",
     "type": "",
     "source": "워크북 · 황조가",
     "in_typebook": false,
     "coreElement": "",
     "weakness1": "워크북(소책자) 고대가요 문항입니다. 틀렸다면 아래 해설로 작품 해석을 다시 확인하세요.",
     "weakness2": "",
     "remediation": "[정답] (가)의 ‘꾀꼬리’는 ‘암수 정답게 노니는데’로 보아 화자의 감정과 대조되는 대상이며, <보기2>의 ‘귓도리’는 ‘슬픈 소릐 제 혼자 우러 녜어’로 보아 감정 이입의 대상이다.  [해설] (가)의 ‘꾀꼬리’는 외로운 화자와 정서적으로 대조되어, 임과 이별해 슬픈 화자와 반대로 ‘암수 정답게 노’닐며 화자의 슬픔을 심화시킨다. <보기2>의 ‘귓도리’는 임과 이별해 슬픈 화자의 감정을 이입하여 ‘슬픈 소릐 제 혼자 우러 녜어’ 등으로 표현한다.",
     "parentNote": "",
     "note": "",
     "해설": "[정답] (가)의 ‘꾀꼬리’는 ‘암수 정답게 노니는데’로 보아 화자의 감정과 대조되는 대상이며, <보기2>의 ‘귓도리’는 ‘슬픈 소릐 제 혼자 우러 녜어’로 보아 감정 이입의 대상이다.  [해설] (가)의 ‘꾀꼬리’는 외로운 화자와 정서적으로 대조되어, 임과 이별해 슬픈 화자와 반대로 ‘암수 정답게 노’닐며 화자의 슬픔을 심화시킨다. <보기2>의 ‘귓도리’는 임과 이별해 슬픈 화자의 감정을 이입하여 ‘슬픈 소릐 제 혼자 우러 녜어’ 등으로 표현한다.",
     "answer": "",
     "label": "32번"
    },
    {
     "no": 39,
     "id": "G1-39",
     "three": false,
     "wr": null,
     "area": "고대가요",
     "type": "",
     "source": "워크북 · 황조가",
     "in_typebook": false,
     "coreElement": "",
     "weakness1": "워크북(소책자) 고대가요 문항입니다. 틀렸다면 아래 해설로 작품 해석을 다시 확인하세요.",
     "weakness2": "",
     "remediation": "(가)의 ‘꾀꼬리’는 시적 화자의 처지와 대조되는 객관적 상관물이다. ‘꾀꼬리’는 암수 서로 정다우나 화자는 함께 돌아갈 대상이 없어 외로움을 느낀다. (가)는 ‘외로워라’에 정서가 직접 드러나고, <보기>는 ‘산봉우리’를 의인화한다.",
     "parentNote": "",
     "note": "",
     "해설": "(가)의 ‘꾀꼬리’는 시적 화자의 처지와 대조되는 객관적 상관물이다. ‘꾀꼬리’는 암수 서로 정다우나 화자는 함께 돌아갈 대상이 없어 외로움을 느낀다. (가)는 ‘외로워라’에 정서가 직접 드러나고, <보기>는 ‘산봉우리’를 의인화한다.",
     "answer": "",
     "label": "33번"
    },
    {
     "no": 40,
     "id": "G1-40",
     "three": false,
     "wr": null,
     "area": "고대가요",
     "type": "",
     "source": "워크북 · 황조가",
     "in_typebook": false,
     "coreElement": "",
     "weakness1": "워크북(소책자) 고대가요 문항입니다. 틀렸다면 아래 해설로 작품 해석을 다시 확인하세요.",
     "weakness2": "",
     "remediation": "㉠은 화자의 처지와 대비되어 이별의 슬픔을 강조하는 객관적 상관물이다. 사랑하는 사람과 이별한 화자와 달리 암수가 정다운 꾀꼬리의 모습은 화자의 쓸쓸함을 심화시킨다. 나머지는 모두 감정 이입의 대상이다.",
     "parentNote": "",
     "note": "",
     "해설": "㉠은 화자의 처지와 대비되어 이별의 슬픔을 강조하는 객관적 상관물이다. 사랑하는 사람과 이별한 화자와 달리 암수가 정다운 꾀꼬리의 모습은 화자의 쓸쓸함을 심화시킨다. 나머지는 모두 감정 이입의 대상이다.",
     "answer": "",
     "label": "34번"
    },
    {
     "no": 41,
     "id": "G1-41",
     "three": false,
     "wr": null,
     "area": "고대가요",
     "type": "",
     "source": "워크북 · 황조가",
     "in_typebook": false,
     "coreElement": "",
     "weakness1": "워크북(소책자) 고대가요 문항입니다. 틀렸다면 아래 해설로 작품 해석을 다시 확인하세요.",
     "weakness2": "",
     "remediation": "<보기>는 고려의 멸망에서 무상함과 안타까움을 느낀다. (가)는 ‘꾀꼬리’와 ‘나’의 처지가 대조되고, <보기>는 자연과 인간의 모습이 대조된다. 두 작품 모두 독백체이다. (가)는 화자의 시선이 외부에서 내면으로 이동하는 선경후정 방식이며, 마지막 구절에서 설의법으로 외로움을 토로한다. (가)는 시적 대상을 시각적 이미지로 형상화해 다정한 모습으로 외로움을 부각하고, <보기>는 자연사와 인간사를 대조해 인간사의 무상함을 강조한다. 대상에 대한 비판적 견해를 드러내지는 않는다.",
     "parentNote": "",
     "note": "",
     "해설": "<보기>는 고려의 멸망에서 무상함과 안타까움을 느낀다. (가)는 ‘꾀꼬리’와 ‘나’의 처지가 대조되고, <보기>는 자연과 인간의 모습이 대조된다. 두 작품 모두 독백체이다. (가)는 화자의 시선이 외부에서 내면으로 이동하는 선경후정 방식이며, 마지막 구절에서 설의법으로 외로움을 토로한다. (가)는 시적 대상을 시각적 이미지로 형상화해 다정한 모습으로 외로움을 부각하고, <보기>는 자연사와 인간사를 대조해 인간사의 무상함을 강조한다. 대상에 대한 비판적 견해를 드러내지는 않는다.",
     "answer": "",
     "label": "35번"
    },
    {
     "no": 42,
     "id": "G1-42",
     "three": false,
     "wr": null,
     "area": "고대가요",
     "type": "",
     "source": "워크북 · 황조가",
     "in_typebook": false,
     "coreElement": "",
     "weakness1": "워크북(소책자) 고대가요 문항입니다. 틀렸다면 아래 해설로 작품 해석을 다시 확인하세요.",
     "weakness2": "",
     "remediation": "‘꾀꼬리’는 화자와 대조되어 암수가 다정해 화자의 외로움을 부각하는 객관적 상관물이다. ‘곳고리새’는 사월에 돌아왔지만 ‘녹사님’은 돌아오지 않아 시적 대상과 대조되어 그리움을 부각하는 객관적 상관물이다. 나머지는 ‘물’·‘새’·‘귀또리’ 등에 감정을 이입한 대상이다.",
     "parentNote": "",
     "note": "",
     "해설": "‘꾀꼬리’는 화자와 대조되어 암수가 다정해 화자의 외로움을 부각하는 객관적 상관물이다. ‘곳고리새’는 사월에 돌아왔지만 ‘녹사님’은 돌아오지 않아 시적 대상과 대조되어 그리움을 부각하는 객관적 상관물이다. 나머지는 ‘물’·‘새’·‘귀또리’ 등에 감정을 이입한 대상이다.",
     "answer": "",
     "label": "36번"
    }
   ]
  },
  {
   "key": "s4",
   "title": "워크북(소책자) · 정읍사",
   "range": "소책자 · 정읍사",
   "questions": [
    {
     "no": 43,
     "id": "G1-43",
     "three": false,
     "wr": null,
     "area": "고대가요",
     "type": "",
     "source": "워크북 · 정읍사",
     "in_typebook": false,
     "coreElement": "",
     "weakness1": "워크북(소책자) 고대가요 문항입니다. 틀렸다면 아래 해설로 작품 해석을 다시 확인하세요.",
     "weakness2": "",
     "remediation": "[정답] 내 가논 ᄃᆡ  [해설] ‘어긔야 내 가논 ᄃᆡ 졈그ᄅᆞᆯ셰라’에서 ‘내’는 임, 나(화자) 또는 임과 화자로 해석할 수 있다. 이때 ‘내 가논 ᄃᆡ’는 각각 ‘내 임의 귀갓길’, ‘내가 임을 마중 가는 길’, ‘임과 내 앞에 놓인 앞으로의 인생길’로 이해할 수 있다.",
     "parentNote": "",
     "note": "",
     "해설": "[정답] 내 가논 ᄃᆡ  [해설] ‘어긔야 내 가논 ᄃᆡ 졈그ᄅᆞᆯ셰라’에서 ‘내’는 임, 나(화자) 또는 임과 화자로 해석할 수 있다. 이때 ‘내 가논 ᄃᆡ’는 각각 ‘내 임의 귀갓길’, ‘내가 임을 마중 가는 길’, ‘임과 내 앞에 놓인 앞으로의 인생길’로 이해할 수 있다.",
     "answer": "",
     "label": "37번"
    },
    {
     "no": 44,
     "id": "G1-44",
     "three": false,
     "wr": null,
     "area": "고대가요",
     "type": "",
     "source": "워크북 · 정읍사",
     "in_typebook": false,
     "coreElement": "",
     "weakness1": "워크북(소책자) 고대가요 문항입니다. 틀렸다면 아래 해설로 작품 해석을 다시 확인하세요.",
     "weakness2": "",
     "remediation": "[정답] (1) ㉣ (2) ‘드ᄃᆡ 욜셰라’는 ‘디딜까 두렵습니다.’의 뜻으로, 남편에게 나쁜 일이 생길까 염려하는 화자의 마음을 엿볼 수 있다.  [해설] 종결어미 ‘~ㄹ셰라’는 ‘~할까 두렵습니다.’의 의미로, ‘디ᄃᆡ 욜셰라’는 ‘디딜까 두렵습니다.’로 해석된다. 이는 ‘져재’에 있는 남편에게 나쁜 일이 생길까 염려하는 화자의 마음을 확인할 수 있는 구절이다.",
     "parentNote": "",
     "note": "",
     "해설": "[정답] (1) ㉣ (2) ‘드ᄃᆡ 욜셰라’는 ‘디딜까 두렵습니다.’의 뜻으로, 남편에게 나쁜 일이 생길까 염려하는 화자의 마음을 엿볼 수 있다.  [해설] 종결어미 ‘~ㄹ셰라’는 ‘~할까 두렵습니다.’의 의미로, ‘디ᄃᆡ 욜셰라’는 ‘디딜까 두렵습니다.’로 해석된다. 이는 ‘져재’에 있는 남편에게 나쁜 일이 생길까 염려하는 화자의 마음을 확인할 수 있는 구절이다.",
     "answer": "",
     "label": "38번"
    },
    {
     "no": 45,
     "id": "G1-45",
     "three": false,
     "wr": null,
     "area": "고대가요",
     "type": "",
     "source": "워크북 · 정읍사",
     "in_typebook": false,
     "coreElement": "",
     "weakness1": "워크북(소책자) 고대가요 문항입니다. 틀렸다면 아래 해설로 작품 해석을 다시 확인하세요.",
     "weakness2": "",
     "remediation": "ⓐ는 천지신명으로 화자에게 기원의 대상이 맞지만, ⓑ는 화자가 벗으로 삼고 싶어 하며 예찬하는 대상으로, 화자가 물아일체(物我一體)적 정서를 바탕으로 동일시하는 소재라고 볼 수 없다.",
     "parentNote": "",
     "note": "",
     "해설": "ⓐ는 천지신명으로 화자에게 기원의 대상이 맞지만, ⓑ는 화자가 벗으로 삼고 싶어 하며 예찬하는 대상으로, 화자가 물아일체(物我一體)적 정서를 바탕으로 동일시하는 소재라고 볼 수 없다.",
     "answer": "",
     "label": "39번"
    },
    {
     "no": 46,
     "id": "G1-46",
     "three": false,
     "wr": null,
     "area": "고대가요",
     "type": "",
     "source": "워크북 · 정읍사",
     "in_typebook": false,
     "coreElement": "",
     "weakness1": "워크북(소책자) 고대가요 문항입니다. 틀렸다면 아래 해설로 작품 해석을 다시 확인하세요.",
     "weakness2": "",
     "remediation": "[정답] 어긔야 즌 ᄃᆡ 드욜셰라, 어긔야 내 가논 ᄃᆡ 졈그ᄅᆞᆯ셰라  [해설] ‘~ㄹ셰라’는 의구형 어미로 화자의 두려움을 드러낸다. ‘즌 ᄃᆡ 드욜셰라’는 남편이 위험에 빠질까 걱정하는 것이고, ‘내 가논 ᄃᆡ 졈그ᄅᆞᆯ셰라’는 ‘내’를 ‘남편’으로 해석할 경우 남편의 귀갓길이 어두워질까 걱정하는 것이다.",
     "parentNote": "",
     "note": "",
     "해설": "[정답] 어긔야 즌 ᄃᆡ 드욜셰라, 어긔야 내 가논 ᄃᆡ 졈그ᄅᆞᆯ셰라  [해설] ‘~ㄹ셰라’는 의구형 어미로 화자의 두려움을 드러낸다. ‘즌 ᄃᆡ 드욜셰라’는 남편이 위험에 빠질까 걱정하는 것이고, ‘내 가논 ᄃᆡ 졈그ᄅᆞᆯ셰라’는 ‘내’를 ‘남편’으로 해석할 경우 남편의 귀갓길이 어두워질까 걱정하는 것이다.",
     "answer": "",
     "label": "40번"
    },
    {
     "no": 47,
     "id": "G1-47",
     "three": false,
     "wr": null,
     "area": "고대가요",
     "type": "",
     "source": "워크북 · 정읍사",
     "in_typebook": false,
     "coreElement": "",
     "weakness1": "워크북(소책자) 고대가요 문항입니다. 틀렸다면 아래 해설로 작품 해석을 다시 확인하세요.",
     "weakness2": "",
     "remediation": "화자의 남편이 행상인임을 알게 해 주는 시어는 ‘시장에’라는 뜻을 가지는 ‘져재’이다. ‘하’는 높임의 호격조사이다.",
     "parentNote": "",
     "note": "",
     "해설": "화자의 남편이 행상인임을 알게 해 주는 시어는 ‘시장에’라는 뜻을 가지는 ‘져재’이다. ‘하’는 높임의 호격조사이다.",
     "answer": "",
     "label": "41번"
    },
    {
     "no": 48,
     "id": "G1-48",
     "three": false,
     "wr": null,
     "area": "고대가요",
     "type": "",
     "source": "워크북 · 정읍사",
     "in_typebook": false,
     "coreElement": "",
     "weakness1": "워크북(소책자) 고대가요 문항입니다. 틀렸다면 아래 해설로 작품 해석을 다시 확인하세요.",
     "weakness2": "",
     "remediation": "‘달’은 광명의 상징으로, 행상인의 처가 남편의 무사 귀환을 기원하는 대상이다. 간절하게 기원하는 마음을 달에게 의탁하는 모습이 잘 드러나도록 연출해야 한다.",
     "parentNote": "",
     "note": "",
     "해설": "‘달’은 광명의 상징으로, 행상인의 처가 남편의 무사 귀환을 기원하는 대상이다. 간절하게 기원하는 마음을 달에게 의탁하는 모습이 잘 드러나도록 연출해야 한다.",
     "answer": "",
     "label": "42번"
    },
    {
     "no": 49,
     "id": "G1-49",
     "three": false,
     "wr": null,
     "area": "고대가요",
     "type": "",
     "source": "워크북 · 정읍사",
     "in_typebook": false,
     "coreElement": "",
     "weakness1": "워크북(소책자) 고대가요 문항입니다. 틀렸다면 아래 해설로 작품 해석을 다시 확인하세요.",
     "weakness2": "",
     "remediation": "‘정읍사’의 ‘ᄃᆞᆯ’은 어둠을 밝히는 존재, 남편의 안전을 지켜 주는 존재로 화자가 소망을 기원하는 대상이다. ‘원왕생가’의 ‘달’은 화자의 소원을 전달해 주는 매개체이자 화자가 소원을 비는 기원의 대상이다.",
     "parentNote": "",
     "note": "",
     "해설": "‘정읍사’의 ‘ᄃᆞᆯ’은 어둠을 밝히는 존재, 남편의 안전을 지켜 주는 존재로 화자가 소망을 기원하는 대상이다. ‘원왕생가’의 ‘달’은 화자의 소원을 전달해 주는 매개체이자 화자가 소원을 비는 기원의 대상이다.",
     "answer": "",
     "label": "43번"
    },
    {
     "no": 50,
     "id": "G1-50",
     "three": false,
     "wr": null,
     "area": "고대가요",
     "type": "",
     "source": "워크북 · 정읍사",
     "in_typebook": false,
     "coreElement": "",
     "weakness1": "워크북(소책자) 고대가요 문항입니다. 틀렸다면 아래 해설로 작품 해석을 다시 확인하세요.",
     "weakness2": "",
     "remediation": "‘-ㄹ셰라’는 두려움을 나타내는 어미로 ‘드ᄃᆡ욜셰라’는 ‘디딜까 두렵습니다.’로 풀이된다. 참고로 ‘졈그ᄅᆞᆯ셰라’는 ‘저물까 두렵습니다.’로 풀이되며, 강한 의지를 나타내는 어미가 아니다.",
     "parentNote": "",
     "note": "",
     "해설": "‘-ㄹ셰라’는 두려움을 나타내는 어미로 ‘드ᄃᆡ욜셰라’는 ‘디딜까 두렵습니다.’로 풀이된다. 참고로 ‘졈그ᄅᆞᆯ셰라’는 ‘저물까 두렵습니다.’로 풀이되며, 강한 의지를 나타내는 어미가 아니다.",
     "answer": "",
     "label": "44번"
    },
    {
     "no": 51,
     "id": "G1-51",
     "three": false,
     "wr": null,
     "area": "고대가요",
     "type": "",
     "source": "워크북 · 정읍사",
     "in_typebook": false,
     "coreElement": "",
     "weakness1": "워크북(소책자) 고대가요 문항입니다. 틀렸다면 아래 해설로 작품 해석을 다시 확인하세요.",
     "weakness2": "",
     "remediation": "후렴구는 운율을 형성하는 역할을 하지만 의미를 가지는 것이 아니므로 화자의 마음을 효과적으로 드러내는 데에는 기여하지 않는다.",
     "parentNote": "",
     "note": "",
     "해설": "후렴구는 운율을 형성하는 역할을 하지만 의미를 가지는 것이 아니므로 화자의 마음을 효과적으로 드러내는 데에는 기여하지 않는다.",
     "answer": "",
     "label": "45번"
    },
    {
     "no": 52,
     "id": "G1-52",
     "three": false,
     "wr": null,
     "area": "고대가요",
     "type": "",
     "source": "워크북 · 정읍사",
     "in_typebook": false,
     "coreElement": "",
     "weakness1": "워크북(소책자) 고대가요 문항입니다. 틀렸다면 아래 해설로 작품 해석을 다시 확인하세요.",
     "weakness2": "",
     "remediation": "‘정읍사’에서 ‘달’은 광명의 상징으로 화자가 기원하는 천지신명을 의미하며, 화자와 공간적으로 떨어져 있는 남편과 연결되는 대상이다. 화자의 모습을 정감 있게 형상화한 비유적 표현으로 보기는 어렵다.",
     "parentNote": "",
     "note": "",
     "해설": "‘정읍사’에서 ‘달’은 광명의 상징으로 화자가 기원하는 천지신명을 의미하며, 화자와 공간적으로 떨어져 있는 남편과 연결되는 대상이다. 화자의 모습을 정감 있게 형상화한 비유적 표현으로 보기는 어렵다.",
     "answer": "",
     "label": "46번"
    },
    {
     "no": 53,
     "id": "G1-53",
     "three": false,
     "wr": null,
     "area": "고대가요",
     "type": "",
     "source": "워크북 · 정읍사",
     "in_typebook": false,
     "coreElement": "",
     "weakness1": "워크북(소책자) 고대가요 문항입니다. 틀렸다면 아래 해설로 작품 해석을 다시 확인하세요.",
     "weakness2": "",
     "remediation": "㉠은 밝음을, ㉡은 어두운 곳·위험한 곳을 상징하므로 대립적인 의미를 지닌다. ‘몸짓’은 의미가 부여되기 전의 상태이고 ‘꽃’은 의미가 부여된 존재로 상반된 의미를 가지므로 그 관계가 가장 유사하다.",
     "parentNote": "",
     "note": "",
     "해설": "㉠은 밝음을, ㉡은 어두운 곳·위험한 곳을 상징하므로 대립적인 의미를 지닌다. ‘몸짓’은 의미가 부여되기 전의 상태이고 ‘꽃’은 의미가 부여된 존재로 상반된 의미를 가지므로 그 관계가 가장 유사하다.",
     "answer": "",
     "label": "47번"
    },
    {
     "no": 54,
     "id": "G1-54",
     "three": false,
     "wr": null,
     "area": "고대가요",
     "type": "",
     "source": "워크북 · 정읍사",
     "in_typebook": false,
     "coreElement": "",
     "weakness1": "워크북(소책자) 고대가요 문항입니다. 틀렸다면 아래 해설로 작품 해석을 다시 확인하세요.",
     "weakness2": "",
     "remediation": "(나)는 10구체 향가로 누이의 죽음에 대한 슬픔을 종교적으로 승화시키는 내용이 담겨 있다. 하지만 (가)는 남편의 무사 귀가를 달에게 비는 백제의 가요로, ‘달’을 천지신명·종교적 의미를 띤 기원의 대상으로 볼 수는 있으나 인간사의 괴로움을 종교적으로 승화하는 것과는 관련이 없다.",
     "parentNote": "",
     "note": "",
     "해설": "(나)는 10구체 향가로 누이의 죽음에 대한 슬픔을 종교적으로 승화시키는 내용이 담겨 있다. 하지만 (가)는 남편의 무사 귀가를 달에게 비는 백제의 가요로, ‘달’을 천지신명·종교적 의미를 띤 기원의 대상으로 볼 수는 있으나 인간사의 괴로움을 종교적으로 승화하는 것과는 관련이 없다.",
     "answer": "",
     "label": "48번"
    },
    {
     "no": 55,
     "id": "G1-55",
     "three": false,
     "wr": null,
     "area": "고대가요",
     "type": "",
     "source": "워크북 · 정읍사",
     "in_typebook": false,
     "coreElement": "",
     "weakness1": "워크북(소책자) 고대가요 문항입니다. 틀렸다면 아래 해설로 작품 해석을 다시 확인하세요.",
     "weakness2": "",
     "remediation": "서로 구분하고 개별화하는 빛은 햇볕이다. ‘즌 ᄃᆡ’는 ‘달님’과 대조되는 어둠의 이미지로 위험한 곳을 의미한다. 임이 무사히 귀환하기를 달님에게 빌고 있으며, 화자는 임이 ‘즌 ᄃᆡ’에 빠질까 봐 걱정한다. 서로 어울리게 하고 융합하게 하는 달의 속성은 공간적으로 떨어져 있는 임과 화자를 연결해 줄 수 있다.",
     "parentNote": "",
     "note": "",
     "해설": "서로 구분하고 개별화하는 빛은 햇볕이다. ‘즌 ᄃᆡ’는 ‘달님’과 대조되는 어둠의 이미지로 위험한 곳을 의미한다. 임이 무사히 귀환하기를 달님에게 빌고 있으며, 화자는 임이 ‘즌 ᄃᆡ’에 빠질까 봐 걱정한다. 서로 어울리게 하고 융합하게 하는 달의 속성은 공간적으로 떨어져 있는 임과 화자를 연결해 줄 수 있다.",
     "answer": "",
     "label": "49번"
    },
    {
     "no": 56,
     "id": "G1-56",
     "three": false,
     "wr": null,
     "area": "고대가요",
     "type": "",
     "source": "워크북 · 정읍사",
     "in_typebook": false,
     "coreElement": "",
     "weakness1": "워크북(소책자) 고대가요 문항입니다. 틀렸다면 아래 해설로 작품 해석을 다시 확인하세요.",
     "weakness2": "",
     "remediation": "[정답] 윗글은 고대 가요로 구비 전승되다가 훈민정음 창제 이후 한글로 기록되어 전하고, <보기>는 한시로 한자로 기록되어 전한다. 윗글은 행상 나간 남편의 무사 귀환을 바라는 아내의 간절한 마음을 노래했고, <보기>는 대동강 변에서 느끼는 이별의 슬픔을 노래했다.  [해설] ‘정읍사’는 구비 문학이며 남편의 안녕을 바라는 서정시이고, ‘송인’은 기록 문학(한문 문학)이며 이별의 정한을 노래한 서정시이다. 작가 면에서 윗글은 작자 미상, <보기>는 정지상으로 차이가 있다.",
     "parentNote": "",
     "note": "",
     "해설": "[정답] 윗글은 고대 가요로 구비 전승되다가 훈민정음 창제 이후 한글로 기록되어 전하고, <보기>는 한시로 한자로 기록되어 전한다. 윗글은 행상 나간 남편의 무사 귀환을 바라는 아내의 간절한 마음을 노래했고, <보기>는 대동강 변에서 느끼는 이별의 슬픔을 노래했다.  [해설] ‘정읍사’는 구비 문학이며 남편의 안녕을 바라는 서정시이고, ‘송인’은 기록 문학(한문 문학)이며 이별의 정한을 노래한 서정시이다. 작가 면에서 윗글은 작자 미상, <보기>는 정지상으로 차이가 있다.",
     "answer": "",
     "label": "50번"
    },
    {
     "no": 57,
     "id": "G1-57",
     "three": false,
     "wr": null,
     "area": "고대가요",
     "type": "",
     "source": "워크북 · 정읍사",
     "in_typebook": false,
     "coreElement": "",
     "weakness1": "워크북(소책자) 고대가요 문항입니다. 틀렸다면 아래 해설로 작품 해석을 다시 확인하세요.",
     "weakness2": "",
     "remediation": "㉤은 ‘내 님이 가는 곳’이라는 의미로, 화자는 남편이 가는 곳이 위험할까 봐 걱정한다. 따라서 남편(화자의 임)이 가는 길이 위험할 수 있음을 유추할 수 있다.",
     "parentNote": "",
     "note": "",
     "해설": "㉤은 ‘내 님이 가는 곳’이라는 의미로, 화자는 남편이 가는 곳이 위험할까 봐 걱정한다. 따라서 남편(화자의 임)이 가는 길이 위험할 수 있음을 유추할 수 있다.",
     "answer": "",
     "label": "51번"
    },
    {
     "no": 58,
     "id": "G1-58",
     "three": false,
     "wr": null,
     "area": "고대가요",
     "type": "",
     "source": "워크북 · 정읍사",
     "in_typebook": false,
     "coreElement": "",
     "weakness1": "워크북(소책자) 고대가요 문항입니다. 틀렸다면 아래 해설로 작품 해석을 다시 확인하세요.",
     "weakness2": "",
     "remediation": "(가)는 ‘ᄃᆞᆯ’과 ‘즌 ᄃᆡ’를 대조하여 행상 나간 남편의 안전을 비는 화자의 마음을 드러내고, (나)는 ‘고운 풀빛’과 ‘슬픈 노래’를 대조하여 임과 헤어진 화자의 슬픔을 드러낸다.",
     "parentNote": "",
     "note": "",
     "해설": "(가)는 ‘ᄃᆞᆯ’과 ‘즌 ᄃᆡ’를 대조하여 행상 나간 남편의 안전을 비는 화자의 마음을 드러내고, (나)는 ‘고운 풀빛’과 ‘슬픈 노래’를 대조하여 임과 헤어진 화자의 슬픔을 드러낸다.",
     "answer": "",
     "label": "52번"
    },
    {
     "no": 59,
     "id": "G1-59",
     "three": false,
     "wr": null,
     "area": "고대가요",
     "type": "",
     "source": "워크북 · 정읍사",
     "in_typebook": false,
     "coreElement": "",
     "weakness1": "워크북(소책자) 고대가요 문항입니다. 틀렸다면 아래 해설로 작품 해석을 다시 확인하세요.",
     "weakness2": "",
     "remediation": "㉮는 기원의 대상으로 화자는 ㉮에게 직접 남편의 안전을 빈다. ㉯는 화자의 그리움을 무량수불에게 전해 주는 매개체이다.",
     "parentNote": "",
     "note": "",
     "해설": "㉮는 기원의 대상으로 화자는 ㉮에게 직접 남편의 안전을 빈다. ㉯는 화자의 그리움을 무량수불에게 전해 주는 매개체이다.",
     "answer": "",
     "label": "53번"
    },
    {
     "no": 60,
     "id": "G1-60",
     "three": false,
     "wr": null,
     "area": "고대가요",
     "type": "",
     "source": "워크북 · 정읍사",
     "in_typebook": false,
     "coreElement": "",
     "weakness1": "워크북(소책자) 고대가요 문항입니다. 틀렸다면 아래 해설로 작품 해석을 다시 확인하세요.",
     "weakness2": "",
     "remediation": "‘즌 ᄃᆡ’는 남편의 안전을 위협하는 공간으로, 화자는 ‘즌 ᄃᆡᄅᆞᆯ 드ᄃᆡ올셰라’를 통해 남편이 위험한 일을 겪을까 봐 걱정하는 마음을 드러낸다. 남편의 안전을 지켜 주는 공간이 아니다.",
     "parentNote": "",
     "note": "",
     "해설": "‘즌 ᄃᆡ’는 남편의 안전을 위협하는 공간으로, 화자는 ‘즌 ᄃᆡᄅᆞᆯ 드ᄃᆡ올셰라’를 통해 남편이 위험한 일을 겪을까 봐 걱정하는 마음을 드러낸다. 남편의 안전을 지켜 주는 공간이 아니다.",
     "answer": "",
     "label": "54번"
    },
    {
     "no": 61,
     "id": "G1-61",
     "three": false,
     "wr": null,
     "area": "고대가요",
     "type": "",
     "source": "워크북 · 정읍사",
     "in_typebook": false,
     "coreElement": "",
     "weakness1": "워크북(소책자) 고대가요 문항입니다. 틀렸다면 아래 해설로 작품 해석을 다시 확인하세요.",
     "weakness2": "",
     "remediation": "[정답] (1) 구비 전승되다가 조선 시대에 한글로 기록된 (2) 한국인이 한국인의 사상과 감정을 한국어를 통하여 (3) ‘송인’은 한글이 창제되기 이전에 창작된 한문 문학 작품이기 때문이야.  [해설] (1) ‘정읍사’는 구비 전승되다가 훈민정음 창제 이후 우리 문자로 기록되었다. (3) ‘송인’은 한문으로 창작되었지만, 한글 창제 전 우리나라는 한문을 이용해 문자를 표기했기 때문에 우리 문학에 포함할 수 있다.",
     "parentNote": "",
     "note": "",
     "해설": "[정답] (1) 구비 전승되다가 조선 시대에 한글로 기록된 (2) 한국인이 한국인의 사상과 감정을 한국어를 통하여 (3) ‘송인’은 한글이 창제되기 이전에 창작된 한문 문학 작품이기 때문이야.  [해설] (1) ‘정읍사’는 구비 전승되다가 훈민정음 창제 이후 우리 문자로 기록되었다. (3) ‘송인’은 한문으로 창작되었지만, 한글 창제 전 우리나라는 한문을 이용해 문자를 표기했기 때문에 우리 문학에 포함할 수 있다.",
     "answer": "",
     "label": "55번"
    },
    {
     "no": 62,
     "id": "G1-62",
     "three": false,
     "wr": null,
     "area": "고대가요",
     "type": "",
     "source": "워크북 · 정읍사",
     "in_typebook": false,
     "coreElement": "",
     "weakness1": "워크북(소책자) 고대가요 문항입니다. 틀렸다면 아래 해설로 작품 해석을 다시 확인하세요.",
     "weakness2": "",
     "remediation": "(가)는 구전되다가 조선시대에 국문으로 기록되었고, (다)는 한시이므로 한자로 기록되어 전한다. (가)에서는 명암의 대조를 통해 아내의 걱정을 드러내고, (다)는 3구와 4구에서 도치법·과장법·설의법을 사용해 이별의 정한을 드러낸다. (다)는 한시로 일정한 위치의 한자음을 통해 운율을 형성하는 음위율이 드러나며 음보율은 드러나지 않는다. (다)는 한자로 기록되었지만 고려시대 우리나라 작가가 이별의 한과 슬픔이라는 정서를 표현하였고, 이때의 한자는 동아시아의 문어로 사용되었으므로 (다)도 한국문학으로 볼 수 있다.",
     "parentNote": "",
     "note": "",
     "해설": "(가)는 구전되다가 조선시대에 국문으로 기록되었고, (다)는 한시이므로 한자로 기록되어 전한다. (가)에서는 명암의 대조를 통해 아내의 걱정을 드러내고, (다)는 3구와 4구에서 도치법·과장법·설의법을 사용해 이별의 정한을 드러낸다. (다)는 한시로 일정한 위치의 한자음을 통해 운율을 형성하는 음위율이 드러나며 음보율은 드러나지 않는다. (다)는 한자로 기록되었지만 고려시대 우리나라 작가가 이별의 한과 슬픔이라는 정서를 표현하였고, 이때의 한자는 동아시아의 문어로 사용되었으므로 (다)도 한국문학으로 볼 수 있다.",
     "answer": "",
     "label": "56번"
    },
    {
     "no": 63,
     "id": "G1-63",
     "three": false,
     "wr": null,
     "area": "고대가요",
     "type": "",
     "source": "워크북 · 정읍사",
     "in_typebook": false,
     "coreElement": "",
     "weakness1": "워크북(소책자) 고대가요 문항입니다. 틀렸다면 아래 해설로 작품 해석을 다시 확인하세요.",
     "weakness2": "",
     "remediation": "㉣은 남편이 지고 있는 짐을 내려놓아 위험한 곳에 빠지지 않고 무사히 귀환하기를 바라는 마음이 드러난다. 남편이 행상 나간 지 오래되었음을 짐작하게 한다는 설명은 적절하지 않다.",
     "parentNote": "",
     "note": "",
     "해설": "㉣은 남편이 지고 있는 짐을 내려놓아 위험한 곳에 빠지지 않고 무사히 귀환하기를 바라는 마음이 드러난다. 남편이 행상 나간 지 오래되었음을 짐작하게 한다는 설명은 적절하지 않다.",
     "answer": "",
     "label": "57번"
    },
    {
     "no": 64,
     "id": "G1-64",
     "three": false,
     "wr": null,
     "area": "고대가요",
     "type": "",
     "source": "워크북 · 정읍사",
     "in_typebook": false,
     "coreElement": "",
     "weakness1": "워크북(소책자) 고대가요 문항입니다. 틀렸다면 아래 해설로 작품 해석을 다시 확인하세요.",
     "weakness2": "",
     "remediation": "(가)의 ‘져재 녀러신고요’는 ‘달’에게 남편이 있는 곳을 물어보는 표현으로 남편의 안전에 대한 궁금증을 드러내고, (나)는 3구에서 설의법을 사용해 이별의 슬픔을 강조한다. (나)의 3, 4구에서 과장법이 사용되었다. 두 작품 모두 반어적 표현은 사용되지 않았다. (가)는 ‘달’에게 말을 건네는 대화체가, (나)는 독백체가 사용되었다. (가)는 남편의 무사 귀환에 대한 걱정과 간절함이, (나)는 이별의 슬픔이 주된 정서이다.",
     "parentNote": "",
     "note": "",
     "해설": "(가)의 ‘져재 녀러신고요’는 ‘달’에게 남편이 있는 곳을 물어보는 표현으로 남편의 안전에 대한 궁금증을 드러내고, (나)는 3구에서 설의법을 사용해 이별의 슬픔을 강조한다. (나)의 3, 4구에서 과장법이 사용되었다. 두 작품 모두 반어적 표현은 사용되지 않았다. (가)는 ‘달’에게 말을 건네는 대화체가, (나)는 독백체가 사용되었다. (가)는 남편의 무사 귀환에 대한 걱정과 간절함이, (나)는 이별의 슬픔이 주된 정서이다.",
     "answer": "",
     "label": "58번"
    },
    {
     "no": 65,
     "id": "G1-65",
     "three": false,
     "wr": null,
     "area": "고대가요",
     "type": "",
     "source": "워크북 · 정읍사",
     "in_typebook": false,
     "coreElement": "",
     "weakness1": "워크북(소책자) 고대가요 문항입니다. 틀렸다면 아래 해설로 작품 해석을 다시 확인하세요.",
     "weakness2": "",
     "remediation": "㉢ ‘져재’는 ‘시장에’라는 뜻으로 화자의 남편이 행상인임을 알 수 있는 단어이다. ‘어두운 곳’ 혹은 ‘위험한 곳’으로 해석되는 것은 ‘즌 ᄃᆡ’이다.",
     "parentNote": "",
     "note": "",
     "해설": "㉢ ‘져재’는 ‘시장에’라는 뜻으로 화자의 남편이 행상인임을 알 수 있는 단어이다. ‘어두운 곳’ 혹은 ‘위험한 곳’으로 해석되는 것은 ‘즌 ᄃᆡ’이다.",
     "answer": "",
     "label": "59번"
    },
    {
     "no": 66,
     "id": "G1-66",
     "three": false,
     "wr": null,
     "area": "고대가요",
     "type": "",
     "source": "워크북 · 정읍사",
     "in_typebook": false,
     "coreElement": "",
     "weakness1": "워크북(소책자) 고대가요 문항입니다. 틀렸다면 아래 해설로 작품 해석을 다시 확인하세요.",
     "weakness2": "",
     "remediation": "ㄴ. ‘-ㄹ셰라’를 반복하여 남편의 안전에 대한 화자의 걱정을 드러낸다. ㄹ. ‘즌 ᄃᆡ’는 남편에게 닥칠 수 있는 부정적 상황을 비유적으로 나타낸다. ㄱ. ‘달’은 광명의 상징이지만 이상적 세계를 드러내는 것이 아니라 화자의 소망을 들어줄 기원의 대상이다. ㄷ. 극단적 상황이 아니라 부정적 상황을 걱정한다. ㅁ. 화자는 남편의 무사 귀환을 간절히 바라므로 화자의 심리 변화는 나타나지 않는다.",
     "parentNote": "",
     "note": "",
     "해설": "ㄴ. ‘-ㄹ셰라’를 반복하여 남편의 안전에 대한 화자의 걱정을 드러낸다. ㄹ. ‘즌 ᄃᆡ’는 남편에게 닥칠 수 있는 부정적 상황을 비유적으로 나타낸다. ㄱ. ‘달’은 광명의 상징이지만 이상적 세계를 드러내는 것이 아니라 화자의 소망을 들어줄 기원의 대상이다. ㄷ. 극단적 상황이 아니라 부정적 상황을 걱정한다. ㅁ. 화자는 남편의 무사 귀환을 간절히 바라므로 화자의 심리 변화는 나타나지 않는다.",
     "answer": "",
     "label": "60번"
    }
   ]
  }
 ],
 "studyCheck": [
  {
   "num": 1,
   "tag": "done",
   "q": "이번 과제, 어디까지 했나요?",
   "opts": [
    "전부 끝냄",
    "대부분(70% 이상)",
    "절반쯤",
    "조금만(30% 이하)",
    "아직 시작 못 함"
   ]
  },
  {
   "num": 2,
   "tag": "dueDate",
   "type": "date",
   "q": "남은 분량을 언제까지 끝낼 건가요? (완수 예정일)",
   "showIf": {
    "q": 1,
    "minIndex": 1
   }
  },
  {
   "num": 3,
   "tag": "duePledge",
   "q": "완수 약속",
   "opts": [
    "오늘 안에",
    "내일까지",
    "이번 주 안",
    "다음 수업 전까지",
    "솔직히 자신 없음"
   ],
   "showIf": {
    "q": 1,
    "minIndex": 1
   }
  },
  {
   "num": 4,
   "tag": "timeliness",
   "q": "제출 시점은 마감 기준 어땠나요?",
   "opts": [
    "여유 있게 미리",
    "마감 임박해서",
    "마감 지나서(지각)",
    "아직 미제출"
   ]
  },
  {
   "num": 5,
   "tag": "review",
   "q": "채점·오답 정리까지 했나요?",
   "opts": [
    "채점 + 오답 정리까지",
    "채점만 함",
    "풀기만 하고 채점 안 함"
   ]
  },
  {
   "num": 6,
   "tag": "trend",
   "q": "최근 과제들, 스스로 평가하면?",
   "opts": [
    "매번 빠짐없이 함",
    "대체로 하는 편",
    "자주 빠지거나 밀림",
    "거의 못 따라감"
   ]
  },
  {
   "num": 7,
   "tag": "reason",
   "q": "(밀렸거나 못 했다면) 가장 큰 이유는?",
   "opts": [
    "시간이 없어서(다른 과목·학원)",
    "너무 어려워서",
    "깜빡/마감을 놓쳐서",
    "의욕이 안 나서",
    "양이 너무 많아서"
   ],
   "showIf": {
    "q": 1,
    "minIndex": 1
   }
  }
 ],
 "studyDiagnosticCodes": {
  "D_done": {
   "label": "과제 완수",
   "feedback": "이번 과제를 끝까지 완료했어요. 꾸준함이 실력으로 쌓이고 있습니다."
  },
  "D_partial": {
   "label": "부분 완수",
   "feedback": "아직 남은 분량이 있어요. 약속한 기한 안에 꼭 마무리합시다."
  },
  "D_undone": {
   "label": "미완 — 완수 필요",
   "feedback": "이번 과제를 거의 못 했어요. 약속한 날까지 반드시 끝내서 따라잡읍시다."
  },
  "D_ontime": {
   "label": "여유 제출",
   "feedback": "마감에 여유 있게 끝냈어요. 좋은 페이스입니다."
  },
  "D_rush": {
   "label": "마감 임박형",
   "feedback": "마감에 임박해서 끝내는 편이에요. 하루만 앞당겨도 훨씬 안정적입니다."
  },
  "D_late": {
   "label": "지각 제출",
   "feedback": "제출이 늦었어요. 다음 주엔 마감 안에 들어오는 걸 목표로 합시다."
  },
  "D_revfull": {
   "label": "오답 정리까지",
   "feedback": "채점·오답 정리까지 마쳤어요. 가장 중요한 부분을 잘 챙겼습니다."
  },
  "D_norev": {
   "label": "오답 정리 부족",
   "feedback": "채점·오답 정리가 빠졌어요. 틀린 문제를 다시 보는 게 실력 상승의 핵심이에요."
  },
  "D_lagging": {
   "label": "최근 누적 부진",
   "feedback": "최근 과제가 자주 밀리고 있어요. 분량·시간을 함께 점검해 봅시다."
  }
 }
}